__init__.py
_version.py
scaespy.py
cli/__init__.py
cli/scaespy.py
scaespy-1.2.1.dist-info/LICENSE
scaespy-1.2.1.dist-info/METADATA
scaespy-1.2.1.dist-info/WHEEL
scaespy-1.2.1.dist-info/entry_points.txt
scaespy-1.2.1.dist-info/top_level.txt
scaespy-1.2.1.dist-info/RECORD
