Metadata-Version: 2.1
Name: scaespy
Version: 1.2.1
Summary: scAEspy: a tool for autoencoder-based analysis of single-cell RNA sequencing data
Home-page: https://gitlab.com/cvejic-group/scaespy
Author: Andrea Tangherloni
Author-email: andrea.tangherloni@unibg.it
License: LICENSE
Keywords: autoencoder,machine learning,dimensionality reduction,single-cell RNA-data
Platform: UNKNOWN
Classifier: Programming Language :: Python :: 3.5
Classifier: Programming Language :: Python :: 3.7
Requires-Python: >=3.5,<3.8
Requires-Dist: NumPy (>=1.18)
Requires-Dist: Pandas (>=0.25)
Requires-Dist: matplotlib (>=3.1)
Requires-Dist: scikit-learn (>=0.21)
Requires-Dist: seaborn (>=0.9)
Requires-Dist: Tensorflow (<=1.15,>=1.12)
